mdsplit.py
mdsplit-0.4.2.dist-info/LICENSE
mdsplit-0.4.2.dist-info/METADATA
mdsplit-0.4.2.dist-info/WHEEL
mdsplit-0.4.2.dist-info/entry_points.txt
mdsplit-0.4.2.dist-info/RECORD
