Metadata-Version: 2.1
Name: mdsplit
Version: 0.4.2
Summary: Split markdown files at headings
Home-page: https://github.com/markusstraub/mdsplit
License: MIT
Author: Markus Straub
Requires-Python: >=3.7,<4.0
Classifier: License :: OSI Approved :: MIT License
Classifier: Programming Language :: Python :: 3
Classifier: Programming Language :: Python :: 3.7
Classifier: Programming Language :: Python :: 3.8
Classifier: Programming Language :: Python :: 3.9
Classifier: Programming Language :: Python :: 3.10
Classifier: Programming Language :: Python :: 3.11
Classifier: Programming Language :: Python :: 3.12
Project-URL: Repository, https://github.com/markusstraub/mdsplit
